{
  "has_precipitation": true,
  "temperature": 0.95,
  "downfall": 0.9,
  "effects": {
    "sky_color": 7248216,
    "fog_color": 9349228,
    "water_color": 6458178,
    "water_fog_color": 4022066,
    "grass_color_modifier": "swamp",
    "particle": {
      "options": {
        "type": "minecraft:warped_spore"
      },
      "probability": 0.02
    },
    "ambient_sound": "redshift:ambient.aerosol_mangroves.loop",
    "additions_sound": {
      "sound": "redshift:ambient.aerosol_mangroves.additions",
      "tick_chance": 0.008
    },
    "mood_sound": {
      "sound": "minecraft:ambient.crimson_forest.mood",
      "tick_delay": 6000,
      "block_search_extent": 8,
      "offset": 2.0
    }
  },
  "spawners": {},
  "spawn_costs": {},
  "carvers": {},
  "features": [
    [],
    [],
    [
      "redshift:mangrove_mud_spire"
    ],
    [],
    [],
    [],
    [],
    [],
    [],
    [
      "redshift:alien_mangrove"
    ]
  ]
}
